spotlight_sqlalchemy/__init__.py
spotlight_sqlalchemy/errors.py
spotlight_sqlalchemy/plugin.py
spotlight_sqlalchemy/rules.py
spotlight_sqlalchemy-1.0.2.dist-info/LICENSE
spotlight_sqlalchemy-1.0.2.dist-info/METADATA
spotlight_sqlalchemy-1.0.2.dist-info/WHEEL
spotlight_sqlalchemy-1.0.2.dist-info/top_level.txt
spotlight_sqlalchemy-1.0.2.dist-info/RECORD
