Metadata-Version: 2.1
Name: spotlight-sqlalchemy
Version: 1.0.2
Summary: SQLAlchemy plugin for Spotlight.
Home-page: https://github.com/mdoesburg/spotlight-sqlalchemy
Author: Michiel Doesburg
Author-email: michiel@moddix.com
License: MIT
Project-URL: Documentation, https://github.com/mdoesburg/spotlight-sqlalchemy
Project-URL: Code, https://github.com/mdoesburg/spotlight-sqlalchemy
Keywords: spotlight sqlalchemy validation validate
Platform: UNKNOWN
